oidc_jwt_verifier/__init__.py
oidc_jwt_verifier/config.py
oidc_jwt_verifier/errors.py
oidc_jwt_verifier/jwks.py
oidc_jwt_verifier/py.typed
oidc_jwt_verifier/verifier.py
oidc_jwt_verifier-0.1.3.dist-info/METADATA
oidc_jwt_verifier-0.1.3.dist-info/WHEEL
oidc_jwt_verifier-0.1.3.dist-info/top_level.txt
oidc_jwt_verifier-0.1.3.dist-info/RECORD
