Metadata-Version: 2.4
Name: oidc-jwt-verifier
Version: 0.1.3
Summary: Shared, hardened JWT verification core for OIDC/JWKS issuers
Project-URL: Homepage, https://oidc-jwt-verifier.bjornmelin.io/
Project-URL: Documentation, https://oidc-jwt-verifier.bjornmelin.io/
Project-URL: Repository, https://github.com/BjornMelin/oidc-jwt-verifier
Project-URL: Issues, https://github.com/BjornMelin/oidc-jwt-verifier/issues
Project-URL: Changelog, https://github.com/BjornMelin/oidc-jwt-verifier/blob/main/CHANGELOG.md
Classifier: Development Status :: 4 - Beta
Classifier: Intended Audience :: Developers
Classifier: License :: OSI Approved :: MIT License
Classifier: Programming Language :: Python :: 3
Classifier: Programming Language :: Python :: 3.10
Classifier: Programming Language :: Python :: 3.11
Classifier: Programming Language :: Python :: 3.12
Classifier: Programming Language :: Python :: 3.13
Classifier: Programming Language :: Python :: 3.14
Classifier: Typing :: Typed
Requires-Python: >=3.10
Requires-Dist: pyjwt[crypto]>=2.10.1
Provides-Extra: dev
Requires-Dist: build>=1.2.2; extra == "dev"
Requires-Dist: pytest>=8.0.0; extra == "dev"
Requires-Dist: pytest-cov>=4.1.0; extra == "dev"
Requires-Dist: ruff>=0.8.0; extra == "dev"
Requires-Dist: mypy>=1.13.0; extra == "dev"
Requires-Dist: bandit[toml]>=1.7.0; extra == "dev"
Provides-Extra: docs
Requires-Dist: mkdocs-material>=9.5.0; extra == "docs"
Requires-Dist: mkdocstrings[python]>=0.27.0; extra == "docs"
Requires-Dist: mkdocs-autorefs>=1.2.0; extra == "docs"
